MANIFEST.in
README.md
VERSION
setup.py
aegisx.ext.cve.egg-info/PKG-INFO
aegisx.ext.cve.egg-info/SOURCES.txt
aegisx.ext.cve.egg-info/dependency_links.txt
aegisx.ext.cve.egg-info/requires.txt
aegisx.ext.cve.egg-info/top_level.txt
aegisx/ext/cve/__init__.py
aegisx/ext/cve/package.json